libra_toolbox/__init__.py
libra_toolbox/_version.py
libra_toolbox/neutron_detection/__init__.py
libra_toolbox/neutron_detection/activation_foils/__init__.py
libra_toolbox/neutron_detection/activation_foils/calculations.py
libra_toolbox/neutron_detection/activation_foils/calibration.py
libra_toolbox/neutron_detection/activation_foils/compass.py
libra_toolbox/neutron_detection/activation_foils/explicit.py
libra_toolbox/neutron_detection/activation_foils/settings.py
libra_toolbox/neutron_detection/diamond/__init__.py
libra_toolbox/neutron_detection/diamond/process_data.py
libra_toolbox/neutron_detection/diamond/prt.py
libra_toolbox/neutronics/A325_generator_diamond.h5
libra_toolbox/neutronics/__init__.py
libra_toolbox/neutronics/materials.py
libra_toolbox/neutronics/neutron_source.py
libra_toolbox/neutronics/vault.py
libra_toolbox/tritium/__init__.py
libra_toolbox/tritium/lsc_measurements.py
libra_toolbox/tritium/model.py
libra_toolbox/tritium/plotting.py
libra_toolbox-0.9.3.dist-info/licenses/LICENSE
libra_toolbox-0.9.3.dist-info/METADATA
libra_toolbox-0.9.3.dist-info/WHEEL
libra_toolbox-0.9.3.dist-info/top_level.txt
libra_toolbox-0.9.3.dist-info/RECORD
