Metadata-Version: 2.4
Name: libra-toolbox
Version: 0.9.3
Summary: Design and analysis tools for LIBRA project
Author-email: Remi Delaporte-Mathurin <remidm@mit.edu>
License: MIT License
Requires-Python: >=3.10
License-File: LICENSE
Requires-Dist: numpy
Requires-Dist: pint
Requires-Dist: scipy
Requires-Dist: matplotlib
Requires-Dist: sympy
Requires-Dist: pandas
Requires-Dist: h5py
Requires-Dist: uproot
Requires-Dist: h5py
Provides-Extra: neutronics
Requires-Dist: openmc-data-downloader; extra == "neutronics"
Provides-Extra: tests
Requires-Dist: pytest>=5.4.3; extra == "tests"
Requires-Dist: pytest-cov; extra == "tests"
Requires-Dist: nbconvert; extra == "tests"
Requires-Dist: ipykernel; extra == "tests"
Requires-Dist: requests; extra == "tests"
Dynamic: license-file
